interactions_restful/__init__.py
interactions_restful/abc.py
interactions_restful/decorators.py
interactions_restful/manager.py
interactions_restful/py.typed
interactions_restful/backends/fastapi.py
interactions_restful/backends/quart.py
interactions_restful-2.0.0.dist-info/LICENSE
interactions_restful-2.0.0.dist-info/METADATA
interactions_restful-2.0.0.dist-info/WHEEL
interactions_restful-2.0.0.dist-info/top_level.txt
interactions_restful-2.0.0.dist-info/RECORD
