Metadata-Version: 2.1
Name: interactions-restful
Version: 2.0.0
Summary: A library for interactions.py allowing runtime API structures
Home-page: https://github.com/interactions-py/restful
Author: Damego
Author-email: damego.dev@gmail.com
License: MIT
Classifier: Intended Audience :: Developers
Classifier: License :: OSI Approved :: MIT License
Classifier: Natural Language :: English
Classifier: Operating System :: OS Independent
Classifier: Programming Language :: Python :: 3
Classifier: Programming Language :: Python :: 3.10
Classifier: Programming Language :: Python :: 3.11
Classifier: Topic :: Internet
Classifier: Topic :: Software Development :: Libraries :: Python Modules
Classifier: Topic :: Software Development :: Libraries
Classifier: Topic :: Utilities
Requires-Python: >=3.10
License-File: LICENSE
Requires-Dist: discord-py-interactions <6.0.0,>=5.0.0
Provides-Extra: daphne
Requires-Dist: daphne >=4.0.0 ; extra == 'daphne'
Provides-Extra: fastapi
Requires-Dist: fastapi >=0.92.0 ; extra == 'fastapi'
Provides-Extra: hypercorn
Requires-Dist: hypercorn >=0.14.0 ; extra == 'hypercorn'
Provides-Extra: quart
Requires-Dist: quart >=0.15.0 ; extra == 'quart'
Provides-Extra: uvicorn
Requires-Dist: uvicorn >=0.15.0 ; extra == 'uvicorn'
